pygame_imslider/__init__.py
pygame_imslider/animations.py
pygame_imslider/dot.png
pygame_imslider/layouts.py
pygame_imslider/left.png
pygame_imslider/renderers.py
pygame_imslider/right.png
pygame_imslider/slider.py
pygame_imslider/sprites.py
pygame_imslider/examples/__init__.py
pygame_imslider/examples/default.py
pygame_imslider/examples/fade.py
pygame_imslider/examples/focus.py
pygame_imslider/examples/multiple.py
pygame_imslider/examples/one_per_move.py
pygame_imslider/examples/small_loop.py
pygame_imslider/examples/images/__init__.py
pygame_imslider/examples/images/character0.png
pygame_imslider/examples/images/character1.png
pygame_imslider/examples/images/character2.png
pygame_imslider/examples/images/character3.png
pygame_imslider/examples/images/character4.png
pygame_imslider/examples/images/character5.png
pygame_imslider/examples/images/character6.png
pygame_imslider/examples/images/character7.png
pygame_imslider/examples/images/character8.png
pygame_imslider/examples/images/character9.png
pygame_imslider-1.0.2.dist-info/LICENSE
pygame_imslider-1.0.2.dist-info/METADATA
pygame_imslider-1.0.2.dist-info/WHEEL
pygame_imslider-1.0.2.dist-info/top_level.txt
pygame_imslider-1.0.2.dist-info/RECORD
