Metadata-Version: 2.1
Name: pygame-imslider
Version: 1.0.2
Summary: Flexible images slider highly customizable for pygame.
Home-page: https://github.com/anxuae/pygame-imslider
Download-URL: https://github.com/anxuae/pygame-imslider/archive/1.0.2.tar.gz
Author: Antoine Rousseaux
Keywords: pygame,widget
Platform: unix
Platform: linux
Classifier: Development Status :: 5 - Production/Stable
Classifier: Environment :: Other Environment
Classifier: Intended Audience :: Developers
Classifier: License :: OSI Approved :: GNU General Public License v3 or later (GPLv3+)
Classifier: Operating System :: POSIX :: Linux
Classifier: Programming Language :: Python :: 3.6
Classifier: Programming Language :: Python :: 3.7
Classifier: Programming Language :: Python :: 3.8
Classifier: Programming Language :: Python :: 3.9
Classifier: Natural Language :: English
Classifier: Topic :: Software Development :: Libraries :: pygame
Requires-Python: >=3.6
License-File: LICENSE
Requires-Dist: pygame
